app_version/__init__.py
app_version/core.py
app_version-1.0.1.dist-info/DESCRIPTION.rst
app_version-1.0.1.dist-info/METADATA
app_version-1.0.1.dist-info/RECORD
app_version-1.0.1.dist-info/WHEEL
app_version-1.0.1.dist-info/metadata.json
app_version-1.0.1.dist-info/top_level.txt
app_version-1.0.1.dist-info/zip-safe
app_version.egg-info/PKG-INFO
app_version.egg-info/SOURCES.txt
app_version.egg-info/dependency_links.txt
app_version.egg-info/top_level.txt
app_version.egg-info/zip-safe
